[
    {
        "author": "Guy de Maupassant",
        "book": "Bel-Ami",
        "quote": "Happiness is not something ready-made. It comes from your own actions."
    },
    {
        "author": "Guy de Maupassant",
        "book": "Bel-Ami",
        "quote": "To be happy, you must be content with the life you have and the people around you."
    },
    {
        "author": "Guy de Maupassant",
        "book": "Bel-Ami",
        "quote": "A man who is afraid of dying is not truly living."
    },
    {
        "author": "Guy de Maupassant",
        "book": "Bel-Ami",
        "quote": "The only way to make sure a man’s life is his own is to free him from the fear of death."
    },
    {
        "author": "Guy de Maupassant",
        "book": "Bel-Ami",
        "quote": "Love is a tricky thing; it’s fleeting and full of doubt."
    },
    {
        "author": "Guy de Maupassant",
        "book": "Bel-Ami",
        "quote": "The greatest happiness of a man is to conquer his own desires."
    },
    {
        "author": "Guy de Maupassant",
        "book": "Bel-Ami",
        "quote": "We all have dreams, but the harsh reality of life often destroys them."
    },
    {
        "author": "Guy de Maupassant",
        "book": "Bel-Ami",
        "quote": "The pursuit of wealth often leads us to an empty life."
    },
    {
        "author": "Guy de Maupassant",
        "book": "Bel-Ami",
        "quote": "A man without ambition is nothing."
    },
    {
        "author": "Guy de Maupassant",
        "book": "Bel-Ami",
        "quote": "The world judges us by our actions, but our true selves are hidden beneath the surface."
    },
    {
        "author": "Guy de Maupassant",
        "book": "The Necklace",
        "quote": "The things we desire most in life are often the things we cannot have."
    },
    {
        "author": "Guy de Maupassant",
        "book": "The Necklace",
        "quote": "A woman is always ready to sacrifice her happiness for the sake of others."
    },
    {
        "author": "Guy de Maupassant",
        "book": "The Necklace",
        "quote": "We often fail to appreciate what we have until it’s too late."
    },
    {
        "author": "Guy de Maupassant",
        "book": "The Necklace",
        "quote": "Life is full of illusions, and we are often blinded by them."
    },
    {
        "author": "Guy de Maupassant",
        "book": "The Necklace",
        "quote": "Beauty is fleeting, but vanity is eternal."
    },
    {
        "author": "Guy de Maupassant",
        "book": "The Necklace",
        "quote": "The pursuit of material wealth often leads to personal ruin."
    },
    {
        "author": "Guy de Maupassant",
        "book": "The Necklace",
        "quote": "A woman’s beauty is both a blessing and a curse."
    },
    {
        "author": "Guy de Maupassant",
        "book": "The Necklace",
        "quote": "Truth often comes at a steep price."
    },
    {
        "author": "Guy de Maupassant",
        "book": "The Necklace",
        "quote": "Life is a game, but it’s not always fair."
    },
    {
        "author": "Guy de Maupassant",
        "book": "The Necklace",
        "quote": "One cannot escape fate, no matter how hard they try."
    },
    {
        "author": "Guy de Maupassant",
        "book": "The Horla",
        "quote": "I am convinced that the more I see of the world, the less I understand it."
    },
    {
        "author": "Guy de Maupassant",
        "book": "The Horla",
        "quote": "The invisible forces that govern our lives are far stronger than we realize."
    },
    {
        "author": "Guy de Maupassant",
        "book": "The Horla",
        "quote": "There are moments when I fear for my sanity, as I am unable to control what’s happening to me."
    },
    {
        "author": "Guy de Maupassant",
        "book": "The Horla",
        "quote": "Is it possible to live with a mind that is constantly plagued by strange thoughts and visions?"
    },
    {
        "author": "Guy de Maupassant",
        "book": "The Horla",
        "quote": "The human mind is a fragile thing, and the unknown often leads it to madness."
    },
    {
        "author": "Guy de Maupassant",
        "book": "The Horla",
        "quote": "I am convinced that the forces beyond our understanding hold the power to control us."
    },
    {
        "author": "Guy de Maupassant",
        "book": "The Horla",
        "quote": "We are slaves to the invisible, unable to break free from its grasp."
    },
    {
        "author": "Guy de Maupassant",
        "book": "The Horla",
        "quote": "There are things in life that cannot be explained, and we must simply accept them."
    },
    {
        "author": "Guy de Maupassant",
        "book": "The Horla",
        "quote": "The more I try to understand, the more I feel I am losing my grip on reality."
    },
    {
        "author": "Guy de Maupassant",
        "book": "The Horla",
        "quote": "There are moments when the mind loses its way, and the soul feels like it is drifting into the unknown."
    },
    {
        "author": "Guy de Maupassant",
        "book": "The Horla",
        "quote": "Madness is not simply an illness; it is an inevitable consequence of facing the unknown."
    },
    {
        "author": "Guy de Maupassant",
        "book": "The Horla",
        "quote": "Isn’t it strange how the invisible can make us feel so helpless and weak?"
    }
]